{
    "public/admin_filter_macros.html": {
        "version_id": 2000070,
        "version_string": "2.0.0",
        "hash": "03de74d1522192f7b8ae4677a93b2f84"
    },
    "public/thread_list_macros_whoreplied.html": {
        "version_id": 2000200,
        "version_string": "2.0.2",
        "hash": "f75fe7c763d235cde490a75dba90779e"
    },
    "public/whoreplied.less": {
        "version_id": 2000070,
        "version_string": "2.0.0",
        "hash": "ec827600655d1d65d38147edde32f8bc"
    },
    "public/whoreplied_filter_macros.html": {
        "version_id": 2000200,
        "version_string": "2.0.2",
        "hash": "6ebdcad396155663fc60c24daa4c504e"
    },
    "public/whoreplied_list.html": {
        "version_id": 2000200,
        "version_string": "2.0.2",
        "hash": "b2698cb4c45dfec097542eaf76ed866a"
    }
}